pytorchcocotools/__about__.py
pytorchcocotools/__init__.py
pytorchcocotools/_mask.py
pytorchcocotools/coco.py
pytorchcocotools/cocoeval.py
pytorchcocotools/mask.py
pytorchcocotools/py.typed
pytorchcocotools/internal/__init__.py
pytorchcocotools/internal/cocoeval_types.py
pytorchcocotools/internal/entities.py
pytorchcocotools/internal/mask_api/__init__.py
pytorchcocotools/internal/mask_api/bb_iou.py
pytorchcocotools/internal/mask_api/bb_nms.py
pytorchcocotools/internal/mask_api/rle_area.py
pytorchcocotools/internal/mask_api/rle_decode.py
pytorchcocotools/internal/mask_api/rle_encode.py
pytorchcocotools/internal/mask_api/rle_fr_bbox.py
pytorchcocotools/internal/mask_api/rle_fr_poly.py
pytorchcocotools/internal/mask_api/rle_fr_string.py
pytorchcocotools/internal/mask_api/rle_iou.py
pytorchcocotools/internal/mask_api/rle_merge.py
pytorchcocotools/internal/mask_api/rle_nms.py
pytorchcocotools/internal/mask_api/rle_to_bbox.py
pytorchcocotools/internal/mask_api/rle_to_string.py
pytorchcocotools/internal/structure/__init__.py
pytorchcocotools/internal/structure/additional.py
pytorchcocotools/internal/structure/annotations.py
pytorchcocotools/internal/structure/base.py
pytorchcocotools/internal/structure/categories.py
pytorchcocotools/internal/structure/coco.py
pytorchcocotools/internal/structure/images.py
pytorchcocotools/internal/structure/info.py
pytorchcocotools/internal/structure/licenses.py
pytorchcocotools/internal/structure/results.py
pytorchcocotools/internal/structure/rle.py
pytorchcocotools/lightning/datamodule.py
pytorchcocotools/lightning/metrics/mean_ap.py
pytorchcocotools/torch/dataset.py
pytorchcocotools/torch/label.py
pytorchcocotools/torch/transform.py
pytorchcocotools/utils/dataclass.py
pytorchcocotools/utils/list.py
pytorchcocotools/utils/logging.py
pytorchcocotools/utils/mask.py
pytorchcocotools/utils/optimize.py
pytorchcocotools/utils/poly.py
pytorchcocotools/utils/profiler.py
pytorchcocotools/utils/stage.py
pytorchcocotools/utils/coco/download.py
pytorchcocotools-0.2.0.dist-info/METADATA
pytorchcocotools-0.2.0.dist-info/WHEEL
pytorchcocotools-0.2.0.dist-info/entry_points.txt
pytorchcocotools-0.2.0.dist-info/licenses/LICENSE
pytorchcocotools-0.2.0.dist-info/RECORD
