Metadata-Version: 2.4
Name: pytorchcocotools
Version: 0.2.0
Summary: Unofficial APIs for the MS-COCO dataset using PyTorch
Project-URL: homepage, https://twsl.github.io/pytorchcocotools/
Project-URL: repository, https://github.com/twsl/pytorchcocotools
Project-URL: documentation, https://twsl.github.io/pytorchcocotools/
Author-email: twsl <45483159+twsl@users.noreply.github.com>
License: MIT
License-File: LICENSE
Keywords: coco,lightning,pycocotools,pytorch,pytorch-lightning,pytorchcocotools
Requires-Python: >=3.11
Requires-Dist: matplotlib>=3.10.8
Requires-Dist: torch>=2.10.0
Requires-Dist: torchvision>=0.25.0
Provides-Extra: lightning
Requires-Dist: lightning>=2.6.0; extra == 'lightning'
Provides-Extra: metrics
Requires-Dist: torchmetrics>=1.8.2; extra == 'metrics'
Provides-Extra: profiling
Requires-Dist: line-profiler>=5.0.0; extra == 'profiling'
